pdfinsight/__init__.py
pdfinsight-0.0.14.dist-info/WHEEL
pdfinsight-0.0.14.dist-info/METADATA
pdfinsight-0.0.14.dist-info/RECORD
