Metadata-Version: 2.1
Name: pdfinsight
Version: 0.0.14
Summary: Text Mining & Classification Toolkit
Author-email: erjieyong <erjieyong@gmail.com>
Requires-Python: >=3.8
Classifier: Programming Language :: Python :: 3
Classifier: License :: OSI Approved :: GNU Affero General Public License v3
Classifier: Operating System :: OS Independent
Requires-Dist: PyMuPDF>=1.22.5
Requires-Dist: pandas>=1.5.3
Project-URL: Bug Tracker, https://github.com/erjieyong/PDFInsight/issues
Project-URL: Homepage, https://github.com/erjieyong/PDFInsight
